interweb/__init__.py
interweb/py.typed
interweb-0.1.0.dist-info/METADATA
interweb-0.1.0.dist-info/WHEEL
interweb-0.1.0.dist-info/RECORD
