Metadata-Version: 2.4
Name: interweb
Version: 0.1.0
Summary: Collection of common web utilities.
Author-email: Hart Traveller <ruling_fiction.0b@icloud.com>
Requires-Python: >=3.10
Requires-Dist: httpx>=0.28.1
Requires-Dist: rich>=14.0.0
